collections_undo/__init__.py
collections_undo/_command.py
collections_undo/_const.py
collections_undo/_formatter.py
collections_undo/_reversible.py
collections_undo/_stack.py
collections_undo/_stack_utils.py
collections_undo/_undoable.py
collections_undo/abc.py
collections_undo/containers.py
collections_undo/fmt.py
collections_undo/_containers/__init__.py
collections_undo/_containers/_dataframe.py
collections_undo/_containers/_dict.py
collections_undo/_containers/_list.py
collections_undo/_containers/_ndarray.py
collections_undo/_containers/_set.py
collections_undo-0.0.7.dist-info/LICENSE
collections_undo-0.0.7.dist-info/METADATA
collections_undo-0.0.7.dist-info/WHEEL
collections_undo-0.0.7.dist-info/top_level.txt
collections_undo-0.0.7.dist-info/RECORD
