Metadata-Version: 2.1
Name: collections-undo
Version: 0.0.7
Summary: General undo/redo framework for Python
Download-URL: https://github.com/hanjinliu/collections-undo
Author: Hanjin Liu
Author-email: liuhanjin-sc@g.ecc.u-tokyo.ac.jp
License: MIT
Requires-Python: >=3.8
License-File: LICENSE
Requires-Dist: typing-extensions
